README.rst
setup.py
codequality/__init__.py
codequality/checkers.py
codequality/main.py
codequality/scmhandlers.py
codequality.egg-info/PKG-INFO
codequality.egg-info/SOURCES.txt
codequality.egg-info/dependency_links.txt
codequality.egg-info/entry_points.txt
codequality.egg-info/top_level.txt