Metadata-Version: 1.0
Name: codequality
Version: 0.2-dev
Summary: Simple code checking metatool
Home-page: http://github.com/jenanwise/codequality
Author: UNKNOWN
Author-email: UNKNOWN
License: MIT
Keywords: codequality
Platform: UNKNOWN
